easydict/__init__.py
easydict/easydict.py
bx-easy_dict-0.1.1.dist-info/WHEEL
bx-easy_dict-0.1.1.dist-info/METADATA
bx-easy_dict-0.1.1.dist-info/RECORD
