Metadata-Version: 1.2
Name: bx-easy_dict
Version: 0.1.1
Summary: An simple package offer wrapper for built in dict
Home-page: https://github.com/banxi1988/easydict
License: UNKNOWN
Keywords: dict objectlikedict easydict attribute
Author: Banxi Lee
Author-email: banxi1988@gmail.com
Requires-Python: ~3.3
Classifier: Intended Audience :: Developers
Classifier: License :: OSI Approved :: MIT License
Classifier: Programming Language :: Python :: 2
Classifier: Programming Language :: Python :: 2.6
Classifier: Programming Language :: Python :: 2.7
Classifier: Programming Language :: Python :: 3
Classifier: Programming Language :: Python :: 3.3
Classifier: Programming Language :: Python :: 3.4
Classifier: Programming Language :: Python :: 3.5
Classifier: Topic :: Software Development :: Libraries :: Python Modules
